{
  "frames": {
    "settingsButton_overBg_img": {
      "frame": {
        "x": 1,
        "y": 1,
        "w": 80,
        "h": 80
      },
      "rotated": false,
      "trimmed": false,
      "spriteSourceSize": {
        "x": 0,
        "y": 0,
        "w": 80,
        "h": 80
      },
      "sourceSize": {
        "w": 80,
        "h": 80
      },
      "pivot": {
        "x": 0.5,
        "y": 0.5
      }
    },
    "settingsButton_pressedBg_img": {
      "frame": {
        "x": 1,
        "y": 83,
        "w": 80,
        "h": 80
      },
      "rotated": false,
      "trimmed": false,
      "spriteSourceSize": {
        "x": 0,
        "y": 0,
        "w": 80,
        "h": 80
      },
      "sourceSize": {
        "w": 80,
        "h": 80
      },
      "pivot": {
        "x": 0.5,
        "y": 0.5
      }
    }
  },
  "meta": {
    "app": "IGT Layout Tool - https://github.com/igtinteractive/layout_tool",
    "version": "0.5.2",
    "image": "gamebitmaps-0-4.png",
    "format": "RGBA8888",
    "size": {
      "w": 82,
      "h": 164
    },
    "scale": 1
  }
}